isoautomate/__init__.py
isoautomate/client.py
isoautomate/config.py
isoautomate/exceptions.py
isoautomate/utils.py
isoautomate-0.1.4.dist-info/licenses/License
isoautomate-0.1.4.dist-info/METADATA
isoautomate-0.1.4.dist-info/WHEEL
isoautomate-0.1.4.dist-info/top_level.txt
isoautomate-0.1.4.dist-info/RECORD
