Metadata-Version: 2.4
Name: isoautomate
Version: 0.1.4
Summary: Official Python SDK for the isoAutomate Sovereign Browser Infrastructure, providing connectivity to the isoFleet engine.
Home-page: https://github.com/isoautomate/isoautomate-python
Author: isoAutomate
Author-email: isoAutomate Team <support@isoautomate.com>
License: MIT
Project-URL: Homepage, https://github.com/isoautomate/isoautomate-python
Project-URL: Bug Tracker, https://github.com/isoautomate/isoautomate-python/issues
Requires-Python: >=3.7
License-File: License
Requires-Dist: redis>=4.0.0
Requires-Dist: python-dotenv>=0.19.0
Dynamic: author
Dynamic: home-page
Dynamic: license-file
Dynamic: requires-python
